py_dmmjp/__init__.py
py_dmmjp/actress.py
py_dmmjp/async_client.py
py_dmmjp/author.py
py_dmmjp/client.py
py_dmmjp/commons.py
py_dmmjp/exceptions.py
py_dmmjp/floor.py
py_dmmjp/genre.py
py_dmmjp/maker.py
py_dmmjp/product.py
py_dmmjp/py.typed
py_dmmjp/series.py
py_dmmjp-0.0.12.dist-info/licenses/LICENSE
py_dmmjp-0.0.12.dist-info/METADATA
py_dmmjp-0.0.12.dist-info/WHEEL
py_dmmjp-0.0.12.dist-info/top_level.txt
py_dmmjp-0.0.12.dist-info/RECORD
