Metadata-Version: 2.4
Name: py-dmmjp
Version: 0.0.12
Summary: A Python client library for the DMM API
Author-email: Richard Nguyen <richard@richardhnguyen.com>
Maintainer-email: Richard Nguyen <richard@richardhnguyen.com>
License: MIT License
Project-URL: Homepage, https://github.com/richardnguyen99/py-dmmjp
Project-URL: Documentation, https://py-dmmjp.readthedocs.io/
Project-URL: Repository, https://github.com/richardnguyen99/py-dmmjp.git
Keywords: dmm,api,client,digital,media,affiliate,mypy,pytest,asyncio,http,requests,aiohttp
Classifier: Development Status :: 3 - Alpha
Classifier: Intended Audience :: Developers
Classifier: License :: OSI Approved :: MIT License
Classifier: Operating System :: OS Independent
Classifier: Programming Language :: Python :: 3
Classifier: Programming Language :: Python :: 3.8
Classifier: Programming Language :: Python :: 3.9
Classifier: Programming Language :: Python :: 3.10
Classifier: Programming Language :: Python :: 3.11
Classifier: Programming Language :: Python :: 3.12
Classifier: Topic :: Internet :: WWW/HTTP :: Dynamic Content
Classifier: Topic :: Software Development :: Libraries :: Python Modules
Classifier: Typing :: Typed
Requires-Python: >=3.8
License-File: LICENSE
Requires-Dist: requests>=2.25.0
Requires-Dist: aiohttp>=3.8.0; python_version >= "3.9"
Requires-Dist: typing-extensions>=4.0.0; python_version < "3.10"
Provides-Extra: dev
Requires-Dist: black>=25.0.0; extra == "dev"
Requires-Dist: mypy>=0.991; extra == "dev"
Requires-Dist: pylint>=2.15.0; extra == "dev"
Requires-Dist: pytest>=7.0.0; extra == "dev"
Requires-Dist: pytest-cov>=4.0.0; extra == "dev"
Requires-Dist: pytest-mock>=3.8.0; extra == "dev"
Requires-Dist: responses>=0.22.0; extra == "dev"
Requires-Dist: pre-commit>=2.20.0; extra == "dev"
Requires-Dist: twine>=4.0.0; extra == "dev"
Requires-Dist: build>=0.8.0; extra == "dev"
Provides-Extra: docs
Requires-Dist: sphinx>=5.0.0; extra == "docs"
Requires-Dist: sphinx-rtd-theme>=1.0.0; extra == "docs"
Requires-Dist: myst-parser>=0.18.0; extra == "docs"
Provides-Extra: test
Requires-Dist: pytest>=7.0.0; extra == "test"
Requires-Dist: pytest-cov>=4.0.0; extra == "test"
Requires-Dist: pytest-mock>=3.8.0; extra == "test"
Requires-Dist: pytest-asyncio>=1.2.0; python_version >= "3.9" and extra == "test"
Requires-Dist: responses>=0.22.0; extra == "test"
Dynamic: license-file
